external_task_api_client/__init__.py
external_task_api_client/external_task_api_client_service.py
external_task_api_client/external_task_worker.py
external_task_api_client/test_external_task_client.py
external_task_api_client/external_task_results/__init__.py
external_task_api_client/external_task_results/bpmn_error.py
external_task_api_client/external_task_results/finished.py
external_task_api_client-2.0.33333333333.dist-info/METADATA
external_task_api_client-2.0.33333333333.dist-info/WHEEL
external_task_api_client-2.0.33333333333.dist-info/top_level.txt
external_task_api_client-2.0.33333333333.dist-info/RECORD
